mockie/__init__.py
mockie/test_case.py
mockie-0.0.1.dist-info/DESCRIPTION.rst
mockie-0.0.1.dist-info/METADATA
mockie-0.0.1.dist-info/metadata.json
mockie-0.0.1.dist-info/RECORD
mockie-0.0.1.dist-info/top_level.txt
mockie-0.0.1.dist-info/WHEEL
tests/__init__.py
tests/test_test_case.py
