Metadata-Version: 2.0
Name: mockie
Version: 0.0.1
Summary: Helper classes for easier mocking and patching tests.
Home-page: https://github.com/marcwebbie/mockie
Author: Marcwebbie
Author-email: marcwebbie@gmail.com
License: License :: OSI Approved :: MIT License
Download-URL: https://pypi.python.org/pypi/mockie
Platform: UNKNOWN
Classifier: Development Status :: 4 - Beta
Classifier: Environment :: Console
Classifier: Natural Language :: English
Classifier: Operating System :: OS Independent
Classifier: License :: OSI Approved :: MIT License
Classifier: Programming Language :: Python
Classifier: Programming Language :: Python :: 2.7
Classifier: Programming Language :: Python :: 3
Classifier: Programming Language :: Python :: 3.2
Classifier: Programming Language :: Python :: 3.3
Classifier: Programming Language :: Python :: 3.4
Classifier: Topic :: Software Development :: Libraries
Classifier: Topic :: Software Development :: Libraries :: Python Modules
Classifier: Topic :: Software Development :: Testing
Requires-Dist: mock (==1.0.1)
